cleverbotfree/__init__.py
cleverbotfree-2.3.3.dist-info/LICENSE
cleverbotfree-2.3.3.dist-info/METADATA
cleverbotfree-2.3.3.dist-info/WHEEL
cleverbotfree-2.3.3.dist-info/top_level.txt
cleverbotfree-2.3.3.dist-info/RECORD
