Metadata-Version: 2.1
Name: cleverbotfree
Version: 2.3.3
Summary: Free Alternative For The Cleverbot API
Home-page: https://github.com/plasticuproject/cleverbotfree
Author: plasticuproject
Author-email: plasticuproject@pm.me
License: GPLv3
Download-URL: https://github.com/plasticuproject/cleverbotfree/archive/v2.3.3.tar.gz
Keywords: cleverbot,bot,api,free
Platform: UNKNOWN
Classifier: Development Status :: 5 - Production/Stable
Classifier: Intended Audience :: Developers
Classifier: License :: OSI Approved :: GNU General Public License v3 or later (GPLv3+)
Classifier: Programming Language :: Python :: 3
Classifier: Topic :: Communications :: Chat
Classifier: Topic :: Utilities
License-File: LICENSE
Requires-Dist: playwright
Requires-Dist: fake-useragent
